{
  "$schema": "https://raw.githubusercontent.com/spdx/spdx-spec/v2.2.1/schemas/spdx-schema.json",
  "spdxVersion": "SPDX-2.2",
  "dataLicense": "CC0-1.0",
  "SPDXID": "SPDXRef-DOCUMENT",
  "documentNamespace": "https://spdx.org/spdxdocs/boost-concept-check-x64-windows-1.89.0-3b8eafad-0aeb-49b0-b5ee-153ad249bd44",
  "name": "boost-concept-check:x64-windows@1.89.0 d552126d5140036966688b84e83a9d202e3730ee92561160e7c82b78e9d27db9",
  "creationInfo": {
    "creators": [
      "Tool: vcpkg-2024-06-10-02590c430e4ed9215d27870138c2e579cc338772"
    ],
    "created": "2026-03-03T17:39:03Z"
  },
  "relationships": [
    {
      "spdxElementId": "SPDXRef-port",
      "relationshipType": "GENERATES",
      "relatedSpdxElement": "SPDXRef-binary"
    },
    {
      "spdxElementId": "SPDXRef-port",
      "relationshipType": "CONTAINS",
      "relatedSpdxElement": "SPDXRef-file-0"
    },
    {
      "spdxElementId": "SPDXRef-port",
      "relationshipType": "CONTAINS",
      "relatedSpdxElement": "SPDXRef-file-1"
    },
    {
      "spdxElementId": "SPDXRef-binary",
      "relationshipType": "GENERATED_FROM",
      "relatedSpdxElement": "SPDXRef-port"
    },
    {
      "spdxElementId": "SPDXRef-file-0",
      "relationshipType": "CONTAINED_BY",
      "relatedSpdxElement": "SPDXRef-port"
    },
    {
      "spdxElementId": "SPDXRef-file-1",
      "relationshipType": "CONTAINED_BY",
      "relatedSpdxElement": "SPDXRef-port"
    }
  ],
  "packages": [
    {
      "name": "boost-concept-check",
      "SPDXID": "SPDXRef-port",
      "versionInfo": "1.89.0",
      "downloadLocation": "git+https://github.com/microsoft/vcpkg@4f43e61a82b1e215fbea09fe321fb63b89d70ccf",
      "homepage": "https://www.boost.org/libs/concept_check",
      "licenseConcluded": "BSL-1.0",
      "licenseDeclared": "NOASSERTION",
      "copyrightText": "NOASSERTION",
      "description": "Boost concept_check module",
      "comment": "This is the port (recipe) consumed by vcpkg."
    },
    {
      "name": "boost-concept-check:x64-windows",
      "SPDXID": "SPDXRef-binary",
      "versionInfo": "d552126d5140036966688b84e83a9d202e3730ee92561160e7c82b78e9d27db9",
      "downloadLocation": "NONE",
      "licenseConcluded": "BSL-1.0",
      "licenseDeclared": "NOASSERTION",
      "copyrightText": "NOASSERTION",
      "comment": "This is a binary package built by vcpkg."
    },
    {
      "SPDXID": "SPDXRef-resource-1",
      "name": "boostorg/concept_check",
      "downloadLocation": "git+https://github.com/boostorg/concept_check@boost-1.89.0",
      "licenseConcluded": "NOASSERTION",
      "licenseDeclared": "NOASSERTION",
      "copyrightText": "NOASSERTION",
      "checksums": [
        {
          "algorithm": "SHA512",
          "checksumValue": "2897f939fc23249c5d3466ad570b60c0d33b750eacf9ad8ddcf0cadd923f3830426a0632a3f18951dbc9006bd2a1d77ca2f3b83458038afd78bb7f345bac54c8"
        }
      ]
    }
  ],
  "files": [
    {
      "fileName": "./C:/Users/leo08/AppData/Local/vcpkg/registries/git-trees/4f43e61a82b1e215fbea09fe321fb63b89d70ccf/portfile.cmake",
      "SPDXID": "SPDXRef-file-0",
      "checksums": [
        {
          "algorithm": "SHA256",
          "checksumValue": "2a249307422976d62a1ac3cd5561d449aeaa2b7375e35982f3260160ebeec6b7"
        }
      ],
      "licenseConcluded": "NOASSERTION",
      "copyrightText": "NOASSERTION"
    },
    {
      "fileName": "./C:/Users/leo08/AppData/Local/vcpkg/registries/git-trees/4f43e61a82b1e215fbea09fe321fb63b89d70ccf/vcpkg.json",
      "SPDXID": "SPDXRef-file-1",
      "checksums": [
        {
          "algorithm": "SHA256",
          "checksumValue": "d67d7c1fadefcda29408efc9c9bcea960e16e6c1446ba8ccb8e419435a76e71e"
        }
      ],
      "licenseConcluded": "NOASSERTION",
      "copyrightText": "NOASSERTION"
    }
  ]
}
